dbrecord/__init__.py
dbrecord/interface.py
dbrecord/pdict.py
dbrecord/plist.py
dbrecord/serilize_backend.py
dbrecord/summary.py
dbrecord/utils.py
dbrecord-1.1.4.dist-info/LICENSE
dbrecord-1.1.4.dist-info/METADATA
dbrecord-1.1.4.dist-info/WHEEL
dbrecord-1.1.4.dist-info/top_level.txt
dbrecord-1.1.4.dist-info/RECORD
