Metadata-Version: 2.1
Name: dbrecord
Version: 1.1.4
Summary: sqlite based kv database using for big data IO.
Home-page: https://github.com/pytorch-lumo/dbrecord
Author: sailist
Author-email: sailist@outlook.com
License: Apache License 2.0
Keywords: dbrecord dataset pytorch
Platform: UNKNOWN
Requires-Dist: joblib
